dihash/__init__.py
dihash/benchmark.py
dihash/hash_impl.py
dihash-2.1.dist-info/LICENSE
dihash-2.1.dist-info/METADATA
dihash-2.1.dist-info/WHEEL
dihash-2.1.dist-info/top_level.txt
dihash-2.1.dist-info/RECORD
