Metadata-Version: 2.1
Name: dihash
Version: 2.1
Summary: Python implementation of various directed graph hashing functions.
Author: Caleb Helbling
Author-email: Caleb Helbling <caleb.helbling@yahoo.com>
License: MIT
Project-URL: Homepage, https://github.com/calebh/dihash
Project-URL: Bug Tracker, https://github.com/calebh/dihash/issues
Classifier: Programming Language :: Python :: 3
Classifier: License :: OSI Approved :: MIT License
Classifier: Operating System :: POSIX :: Linux
Classifier: Operating System :: MacOS
Requires-Python: >=3.7
License-File: LICENSE
Requires-Dist: pynauty
Requires-Dist: networkx
